shahr2/__init__.py
shahr2/pymultimailer.py
shahr2.pymultimailer-0.0.3.dist-info/LICENSE
shahr2.pymultimailer-0.0.3.dist-info/METADATA
shahr2.pymultimailer-0.0.3.dist-info/WHEEL
shahr2.pymultimailer-0.0.3.dist-info/top_level.txt
shahr2.pymultimailer-0.0.3.dist-info/RECORD
