Metadata-Version: 2.1
Name: shahr2.pymultimailer
Version: 0.0.3
Summary: Send mail to multiple user at once.
Home-page: https://github.com/shahadathshahriarakash/shahr2.pymultimailer
Author: Shahadath Shahriar
Author-email: shahadathshahriarakash@gmail.com
License: UNKNOWN
Project-URL: Bug Tracker, https://github.com/shahadathshahriarakash/shahr2.pymultimailer/issues
Platform: UNKNOWN
Classifier: Programming Language :: Python :: 3
Classifier: License :: OSI Approved :: MIT License
Classifier: Operating System :: OS Independent
Requires-Python: >=3.8
License-File: LICENSE
